{
  "url": "https://jsnmrs.github.io/since/",
  "requestedUrl": "https://jsnmrs.github.io/since/",
  "timestamp": 1683166886769,
  "ranks": {
    "hundos": 5,
    "performance": 1,
    "accessibility": 12,
    "cumulative": 5
  },
  "lighthouse": {
    "version": "10.0.2",
    "performance": 1,
    "accessibility": 1,
    "bestPractices": 1,
    "seo": 1,
    "total": 400
  },
  "firstContentfulPaint": 796.1637,
  "firstMeaningfulPaint": 796.1637,
  "speedIndex": 796.1637,
  "largestContentfulPaint": 1584.1542,
  "totalBlockingTime": 0,
  "cumulativeLayoutShift": 0,
  "timeToInteractive": 812.1637,
  "maxPotentialFirstInputDelay": 51,
  "timeToFirstByte": 11.202,
  "weight": {
    "summary": "4 requests • 22 KiB",
    "total": 23036,
    "image": 0,
    "imageCount": 0,
    "script": 20863,
    "scriptCount": 2,
    "document": 2054,
    "font": 0,
    "fontCount": 0,
    "stylesheet": 0,
    "stylesheetCount": 0,
    "thirdParty": 23036,
    "thirdPartyCount": 4
  },
  "run": {
    "number": 3,
    "total": 3
  },
  "sidequests": {
    "-weight.total": 4,
    "+weight.total": 10,
    "-weight.document": 2,
    "+weight.document": 12,
    "-weight.script": 2,
    "+weight.script": 3,
    "-weight.image": 1,
    "+weight.image": 8,
    "-weight.font": 1,
    "+weight.font": 6,
    "+weight.fontCount": 2,
    "-timeToFirstByte": 1,
    "-totalBlockingTime": 1,
    "-largestContentfulPaint": 10
  },
  "axe": {
    "passes": 77,
    "violations": 0
  }
}