{
  "url": "https://jasonmorris.com/resume/",
  "requestedUrl": "https://jasonmorris.com/resume/",
  "timestamp": 1689129256073,
  "ranks": {
    "hundos": 7,
    "performance": 2,
    "accessibility": 7,
    "cumulative": 7
  },
  "lighthouse": {
    "version": "10.0.2",
    "performance": 1,
    "accessibility": 1,
    "bestPractices": 1,
    "seo": 1,
    "total": 400
  },
  "firstContentfulPaint": 792.407,
  "firstMeaningfulPaint": 792.407,
  "speedIndex": 792.407,
  "largestContentfulPaint": 1058.4070000000002,
  "totalBlockingTime": 0,
  "cumulativeLayoutShift": 0,
  "timeToInteractive": 792.407,
  "maxPotentialFirstInputDelay": 41,
  "timeToFirstByte": 18.012,
  "weight": {
    "summary": "2 requests • 21 KiB",
    "total": 21041,
    "image": 0,
    "imageCount": 0,
    "script": 0,
    "scriptCount": 0,
    "document": 4913,
    "font": 16128,
    "fontCount": 1,
    "stylesheet": 0,
    "stylesheetCount": 0,
    "thirdParty": 0,
    "thirdPartyCount": 0
  },
  "run": {
    "number": 3,
    "total": 3
  },
  "sidequests": {
    "-weight.total": 5,
    "+weight.total": 9,
    "-weight.document": 8,
    "+weight.document": 6,
    "-weight.script": 1,
    "+weight.script": 5,
    "-weight.image": 1,
    "+weight.image": 8,
    "-weight.font": 2,
    "+weight.font": 1,
    "+weight.fontCount": 1,
    "-timeToFirstByte": 8,
    "-totalBlockingTime": 1,
    "-largestContentfulPaint": 8
  },
  "axe": {
    "passes": 175,
    "violations": 0
  }
}