{
  "url": "https://jsnmrs.github.io/wordup/",
  "requestedUrl": "https://jsnmrs.github.io/wordup/",
  "timestamp": 1697163243897,
  "ranks": {
    "hundos": 12,
    "performance": 12,
    "accessibility": 13,
    "cumulative": 12
  },
  "lighthouse": {
    "version": "11.1.0",
    "performance": 0.99,
    "accessibility": 1,
    "bestPractices": 1,
    "seo": 0.94,
    "total": 393
  },
  "firstContentfulPaint": 792.1433,
  "firstMeaningfulPaint": 792.1433,
  "speedIndex": 1284.8475357846548,
  "largestContentfulPaint": 792.1433,
  "totalBlockingTime": 93.26009999999997,
  "cumulativeLayoutShift": 0.00911260703396538,
  "timeToInteractive": 2976.743000000001,
  "maxPotentialFirstInputDelay": 137,
  "timeToFirstByte": 2.891,
  "weight": {
    "summary": "16 requests • 233.1 KiB",
    "total": 238645,
    "image": 6128,
    "imageCount": 1,
    "script": 219738,
    "scriptCount": 6,
    "document": 1953,
    "font": 0,
    "fontCount": 0,
    "stylesheet": 10533,
    "stylesheetCount": 7,
    "thirdParty": 235337,
    "thirdPartyCount": 2
  },
  "run": {
    "number": 3,
    "total": 3
  },
  "sidequests": {
    "-weight.total": 12,
    "+weight.total": 2,
    "-weight.document": 2,
    "+weight.document": 12,
    "-weight.script": 4,
    "+weight.script": 1,
    "-weight.image": 2,
    "+weight.image": 6,
    "-weight.font": 1,
    "+weight.font": 3,
    "+weight.fontCount": 2,
    "-timeToFirstByte": 1,
    "-totalBlockingTime": 1,
    "-largestContentfulPaint": 2
  },
  "axe": {
    "passes": 522,
    "violations": 1
  }
}