{
  "url": "https://doublegreat.dev/listen/punctuation-in-alt-text/",
  "requestedUrl": "https://doublegreat.dev/listen/punctuation-in-alt-text/",
  "timestamp": 1747190059830,
  "ranks": {
    "hundos": 14,
    "performance": 14,
    "accessibility": 1,
    "cumulative": 14
  },
  "lighthouse": {
    "version": "12.5.1",
    "performance": 0.83,
    "accessibility": 1,
    "bestPractices": 1,
    "seo": 1,
    "total": 383
  },
  "firstContentfulPaint": 858.3508,
  "speedIndex": 858.3508,
  "largestContentfulPaint": 858.3508,
  "totalBlockingTime": 711,
  "cumulativeLayoutShift": 0,
  "timeToInteractive": 1787.3508000000002,
  "maxPotentialFirstInputDelay": 717,
  "timeToFirstByte": 20.318,
  "weight": {
    "summary": "60 requests • 45.2 KiB",
    "total": 46322,
    "image": 0,
    "imageCount": 1,
    "script": 33717,
    "scriptCount": 1,
    "document": 7417,
    "font": 0,
    "fontCount": 0,
    "stylesheet": 0,
    "stylesheetCount": 0,
    "thirdParty": 2628,
    "thirdPartyCount": 1
  },
  "run": {
    "number": 2,
    "total": 3
  },
  "sidequests": {
    "-weight.total": 6,
    "+weight.total": 9,
    "-weight.document": 13,
    "+weight.document": 2,
    "-weight.script": 4,
    "+weight.script": 2,
    "-weight.image": 1,
    "+weight.image": 8,
    "-weight.font": 1,
    "+weight.font": 5,
    "+weight.fontCount": 4,
    "-timeToFirstByte": 6,
    "-totalBlockingTime": 2,
    "-largestContentfulPaint": 7
  },
  "axe": {
    "passes": 2064,
    "violations": 0
  }
}