{
  "url": "https://jasonmorris.com/bikes/bikes-and-barns/",
  "requestedUrl": "https://jasonmorris.com/bikes/bikes-and-barns/",
  "timestamp": 1735439443085,
  "ranks": {
    "hundos": 3,
    "performance": 1,
    "accessibility": 12,
    "cumulative": 3
  },
  "lighthouse": {
    "version": "11.7.1",
    "performance": 1,
    "accessibility": 1,
    "bestPractices": 1,
    "seo": 1,
    "total": 400
  },
  "firstContentfulPaint": 774.8368,
  "firstMeaningfulPaint": 774.8368,
  "speedIndex": 774.8368,
  "largestContentfulPaint": 1057.8368,
  "totalBlockingTime": 0,
  "cumulativeLayoutShift": 0.023024999667812834,
  "timeToInteractive": 774.8368,
  "maxPotentialFirstInputDelay": 16,
  "timeToFirstByte": 9.708,
  "weight": {
    "summary": "5 requests • 78.8 KiB",
    "total": 80646,
    "image": 60101,
    "imageCount": 3,
    "script": 0,
    "scriptCount": 0,
    "document": 4580,
    "font": 15965,
    "fontCount": 1,
    "stylesheet": 0,
    "stylesheetCount": 0,
    "thirdParty": 0,
    "thirdPartyCount": 0
  },
  "run": {
    "number": 2,
    "total": 2
  },
  "sidequests": {
    "-weight.total": 10,
    "+weight.total": 5,
    "-weight.document": 6,
    "+weight.document": 9,
    "-weight.script": 1,
    "+weight.script": 6,
    "-weight.image": 5,
    "+weight.image": 4,
    "-weight.font": 1,
    "+weight.font": 4,
    "+weight.fontCount": 3,
    "-timeToFirstByte": 5,
    "-totalBlockingTime": 1,
    "-largestContentfulPaint": 8
  },
  "axe": {
    "passes": 100,
    "violations": 0
  }
}