{
  "url": "https://bmxfeed.com/video",
  "requestedUrl": "https://bmxfeed.com/video",
  "timestamp": 1676860161569,
  "ranks": {
    "hundos": 1,
    "performance": 5,
    "accessibility": 3,
    "cumulative": 1
  },
  "lighthouse": {
    "version": "9.6.8",
    "performance": 1,
    "accessibility": 1,
    "bestPractices": 1,
    "seo": 1,
    "total": 400
  },
  "firstContentfulPaint": 882.5946,
  "firstMeaningfulPaint": 882.5946,
  "speedIndex": 882.5946,
  "largestContentfulPaint": 1126.5946,
  "totalBlockingTime": 0,
  "cumulativeLayoutShift": 0,
  "timeToInteractive": 882.5946,
  "maxPotentialFirstInputDelay": 39,
  "timeToFirstByte": 204.45700000000002,
  "weight": {
    "summary": "31 requests • 491 KiB",
    "total": 503066,
    "image": 499334,
    "imageCount": 30,
    "script": 0,
    "scriptCount": 0,
    "document": 3732,
    "font": 0,
    "fontCount": 0,
    "stylesheet": 0,
    "stylesheetCount": 0,
    "thirdParty": 0,
    "thirdPartyCount": 0
  },
  "run": {
    "number": 1,
    "total": 3
  },
  "sidequests": {
    "-weight.total": 13,
    "+weight.total": 1,
    "-weight.document": 4,
    "+weight.document": 10,
    "-weight.script": 1,
    "+weight.script": 5,
    "-weight.image": 7,
    "+weight.image": 1,
    "-weight.font": 1,
    "+weight.font": 6,
    "+weight.fontCount": 2,
    "-timeToFirstByte": 13,
    "-totalBlockingTime": 1,
    "-largestContentfulPaint": 12
  },
  "axe": {
    "passes": 391,
    "violations": 0
  }
}