{
  "url": "https://code.jasonmorris.com/wordup/",
  "requestedUrl": "https://code.jasonmorris.com/wordup/",
  "timestamp": 1724379571819,
  "ranks": {
    "hundos": 12,
    "performance": 12,
    "accessibility": 14,
    "cumulative": 12
  },
  "lighthouse": {
    "version": "11.7.0",
    "performance": 0.97,
    "accessibility": 1,
    "bestPractices": 0.96,
    "seo": 1,
    "total": 393
  },
  "firstContentfulPaint": 781.2854,
  "firstMeaningfulPaint": 781.2854,
  "speedIndex": 1306.6159240387,
  "largestContentfulPaint": 2601.7550999999994,
  "totalBlockingTime": 52.5,
  "cumulativeLayoutShift": 0.013018010048521973,
  "timeToInteractive": 2294.2853999999998,
  "maxPotentialFirstInputDelay": 103,
  "timeToFirstByte": 14.908,
  "weight": {
    "summary": "17 requests • 243.2 KiB",
    "total": 249030,
    "image": 13275,
    "imageCount": 2,
    "script": 222998,
    "scriptCount": 6,
    "document": 1809,
    "font": 0,
    "fontCount": 0,
    "stylesheet": 10526,
    "stylesheetCount": 7,
    "thirdParty": 422,
    "thirdPartyCount": 1
  },
  "run": {
    "number": 2,
    "total": 3
  },
  "sidequests": {
    "-weight.total": 12,
    "+weight.total": 3,
    "-weight.document": 1,
    "+weight.document": 14,
    "-weight.script": 5,
    "+weight.script": 1,
    "-weight.image": 2,
    "+weight.image": 7,
    "-weight.font": 1,
    "+weight.font": 4,
    "+weight.fontCount": 3,
    "-timeToFirstByte": 2,
    "-totalBlockingTime": 2,
    "-largestContentfulPaint": 13
  },
  "axe": {
    "passes": 546,
    "violations": 1
  }
}