{
  "url": "https://code.jasonmorris.com/wordup/",
  "requestedUrl": "https://code.jasonmorris.com/wordup/",
  "timestamp": 1739672936633,
  "ranks": {
    "hundos": 12,
    "performance": 12,
    "accessibility": 14,
    "cumulative": 12
  },
  "lighthouse": {
    "version": "11.7.1",
    "performance": 0.96,
    "accessibility": 1,
    "bestPractices": 0.96,
    "seo": 1,
    "total": 392
  },
  "firstContentfulPaint": 783.5584,
  "firstMeaningfulPaint": 783.5584,
  "speedIndex": 783.5584,
  "largestContentfulPaint": 2614.2790999999997,
  "totalBlockingTime": 99,
  "cumulativeLayoutShift": 0.013018010048521973,
  "timeToInteractive": 2307.5584,
  "maxPotentialFirstInputDelay": 190,
  "timeToFirstByte": 18.6,
  "weight": {
    "summary": "17 requests • 243.1 KiB",
    "total": 248964,
    "image": 13353,
    "imageCount": 2,
    "script": 223108,
    "scriptCount": 6,
    "document": 1826,
    "font": 0,
    "fontCount": 0,
    "stylesheet": 10255,
    "stylesheetCount": 7,
    "thirdParty": 422,
    "thirdPartyCount": 1
  },
  "run": {
    "number": 2,
    "total": 3
  },
  "sidequests": {
    "-weight.total": 12,
    "+weight.total": 3,
    "-weight.document": 1,
    "+weight.document": 14,
    "-weight.script": 5,
    "+weight.script": 1,
    "-weight.image": 2,
    "+weight.image": 7,
    "-weight.font": 1,
    "+weight.font": 5,
    "+weight.fontCount": 4,
    "-timeToFirstByte": 10,
    "-totalBlockingTime": 1,
    "-largestContentfulPaint": 13
  },
  "axe": {
    "passes": 546,
    "violations": 1
  }
}