{
  "url": "https://code.jasonmorris.com/wordup/",
  "requestedUrl": "https://code.jasonmorris.com/wordup/",
  "timestamp": 1767667276521,
  "ranks": {
    "hundos": 12,
    "performance": 12,
    "accessibility": 14,
    "cumulative": 12
  },
  "lighthouse": {
    "version": "12.8.2",
    "performance": 0.94,
    "accessibility": 1,
    "bestPractices": 0.96,
    "seo": 1,
    "total": 390
  },
  "firstContentfulPaint": 870.3094,
  "speedIndex": 1114.5587999999932,
  "largestContentfulPaint": 2678.5316000000003,
  "totalBlockingTime": 184,
  "cumulativeLayoutShift": 0.013018010048521973,
  "timeToInteractive": 2678.5316000000003,
  "maxPotentialFirstInputDelay": 175,
  "timeToFirstByte": 93.12299999999999,
  "weight": {
    "summary": "17 requests • 243.1 KiB",
    "total": 248948,
    "image": 13409,
    "imageCount": 2,
    "script": 223110,
    "scriptCount": 6,
    "document": 1850,
    "font": 0,
    "fontCount": 0,
    "stylesheet": 10247,
    "stylesheetCount": 7,
    "thirdParty": 332,
    "thirdPartyCount": 1
  },
  "run": {
    "number": 2,
    "total": 3
  },
  "sidequests": {
    "-weight.total": 13,
    "+weight.total": 2,
    "-weight.document": 1,
    "+weight.document": 14,
    "-weight.script": 5,
    "+weight.script": 1,
    "-weight.image": 1,
    "+weight.image": 7,
    "-weight.font": 1,
    "+weight.font": 5,
    "+weight.fontCount": 4,
    "-timeToFirstByte": 5,
    "-totalBlockingTime": 1,
    "-largestContentfulPaint": 13
  },
  "axe": {
    "passes": 546,
    "violations": 1
  }
}