{
  "url": "https://code.jasonmorris.com/since/",
  "requestedUrl": "https://code.jasonmorris.com/since/",
  "timestamp": 1724206751176,
  "ranks": {
    "hundos": 6,
    "performance": 5,
    "accessibility": 13,
    "cumulative": 6
  },
  "lighthouse": {
    "version": "11.7.0",
    "performance": 1,
    "accessibility": 1,
    "bestPractices": 1,
    "seo": 1,
    "total": 400
  },
  "firstContentfulPaint": 782.8248,
  "firstMeaningfulPaint": 782.8248,
  "speedIndex": 782.8248,
  "largestContentfulPaint": 782.8248,
  "totalBlockingTime": 0,
  "cumulativeLayoutShift": 0,
  "timeToInteractive": 782.8248,
  "maxPotentialFirstInputDelay": 16,
  "timeToFirstByte": 17.142000000000003,
  "weight": {
    "summary": "4 requests • 27.5 KiB",
    "total": 28190,
    "image": 0,
    "imageCount": 0,
    "script": 25890,
    "scriptCount": 2,
    "document": 2003,
    "font": 0,
    "fontCount": 0,
    "stylesheet": 0,
    "stylesheetCount": 0,
    "thirdParty": 24980,
    "thirdPartyCount": 1
  },
  "run": {
    "number": 2,
    "total": 3
  },
  "sidequests": {
    "-weight.total": 6,
    "+weight.total": 9,
    "-weight.document": 2,
    "+weight.document": 13,
    "-weight.script": 3,
    "+weight.script": 3,
    "-weight.image": 1,
    "+weight.image": 9,
    "-weight.font": 1,
    "+weight.font": 4,
    "+weight.fontCount": 3,
    "-timeToFirstByte": 8,
    "-totalBlockingTime": 1,
    "-largestContentfulPaint": 1
  },
  "axe": {
    "passes": 77,
    "violations": 0
  }
}