{
  "url": "https://doublegreat.dev/",
  "requestedUrl": "https://doublegreat.dev/",
  "timestamp": 1751682800926,
  "ranks": {
    "hundos": 4,
    "performance": 9,
    "accessibility": 8,
    "cumulative": 4
  },
  "lighthouse": {
    "version": "12.7.0",
    "performance": 1,
    "accessibility": 1,
    "bestPractices": 1,
    "seo": 1,
    "total": 400
  },
  "firstContentfulPaint": 828.37,
  "speedIndex": 828.37,
  "largestContentfulPaint": 828.37,
  "totalBlockingTime": 0,
  "cumulativeLayoutShift": 0,
  "timeToInteractive": 828.3700000000001,
  "maxPotentialFirstInputDelay": 16,
  "timeToFirstByte": 35.52000000000001,
  "weight": {
    "summary": "6 requests • 62.8 KiB",
    "total": 64257,
    "image": 48461,
    "imageCount": 2,
    "script": 0,
    "scriptCount": 0,
    "document": 6710,
    "font": 0,
    "fontCount": 0,
    "stylesheet": 0,
    "stylesheetCount": 0,
    "thirdParty": 55284,
    "thirdPartyCount": 1
  },
  "run": {
    "number": 1,
    "total": 3
  },
  "sidequests": {
    "-weight.total": 9,
    "+weight.total": 6,
    "-weight.document": 11,
    "+weight.document": 3,
    "-weight.script": 1,
    "+weight.script": 6,
    "-weight.image": 3,
    "+weight.image": 5,
    "-weight.font": 1,
    "+weight.font": 6,
    "+weight.fontCount": 4,
    "-timeToFirstByte": 7,
    "-totalBlockingTime": 1,
    "-largestContentfulPaint": 5
  },
  "axe": {
    "passes": 179,
    "violations": 0
  }
}